rtlsdr/__init__.py
rtlsdr/helpers.py
rtlsdr/librtlsdr.py
rtlsdr/rtlsdr.py
rtlsdr/rtlsdraio.py
rtlsdr/rtlsdrtcp/__init__.py
rtlsdr/rtlsdrtcp/base.py
rtlsdr/rtlsdrtcp/client.py
rtlsdr/rtlsdrtcp/server.py
pyrtlsdr-0.3.0.dist-info/METADATA
pyrtlsdr-0.3.0.dist-info/WHEEL
pyrtlsdr-0.3.0.dist-info/top_level.txt
pyrtlsdr-0.3.0.dist-info/RECORD
