Metadata-Version: 2.1
Name: pyrtlsdr
Version: 0.3.0
Summary: A Python wrapper for librtlsdr (a driver for Realtek RTL2832U based SDR's)
Home-page: https://github.com/pyrtlsdr/pyrtlsdr
Author: roger
License: GPLv3
Project-URL: Documentation, https://pyrtlsdr.readthedocs.io/
Project-URL: Source, https://github.com/pyrtlsdr/pyrtlsdr
Keywords: radio librtlsdr rtlsdr sdr
Platform: any
Classifier: Development Status :: 4 - Beta
Classifier: Environment :: Console
Classifier: Intended Audience :: Developers
Classifier: License :: OSI Approved :: GNU General Public License (GPL)
Classifier: Natural Language :: English
Classifier: Operating System :: OS Independent
Classifier: Programming Language :: Python :: 2
Classifier: Programming Language :: Python :: 2.7
Classifier: Programming Language :: Python :: 3
Classifier: Programming Language :: Python :: 3.8
Classifier: Programming Language :: Python :: 3.9
Classifier: Programming Language :: Python :: 3.10
Classifier: Programming Language :: Python :: 3.11
Classifier: Topic :: Utilities
Provides-Extra: lib
